examples/__init__.py
openrl/__init__.py
openrl/algorithms/__init__.py
openrl/algorithms/a2c.py
openrl/algorithms/base_algorithm.py
openrl/algorithms/behavior_cloning.py
openrl/algorithms/ddpg.py
openrl/algorithms/dqn.py
openrl/algorithms/gail.py
openrl/algorithms/mat.py
openrl/algorithms/ppo.py
openrl/algorithms/sac.py
openrl/algorithms/vdn.py
openrl/arena/__init__.py
openrl/arena/base_arena.py
openrl/arena/two_player_arena.py
openrl/arena/utils.py
openrl/arena/agents/__init__.py
openrl/arena/agents/base_agent.py
openrl/arena/agents/jidi_agent.py
openrl/arena/agents/local_agent.py
openrl/arena/agents/random_agent.py
openrl/arena/games/__init__.py
openrl/arena/games/base_game.py
openrl/arena/games/two_player_game.py
openrl/buffers/__init__.py
openrl/buffers/normal_buffer.py
openrl/buffers/offpolicy_buffer.py
openrl/buffers/offpolicy_replay_data.py
openrl/buffers/replay_data.py
openrl/buffers/utils/__init__.py
openrl/buffers/utils/obs_data.py
openrl/buffers/utils/util.py
openrl/cli/__init__.py
openrl/cli/cli.py
openrl/cli/train.py
openrl/configs/__init__.py
openrl/configs/config.py
openrl/configs/utils.py
openrl/datasets/__init__.py
openrl/datasets/expert_dataset.py
openrl/drivers/__init__.py
openrl/drivers/base_driver.py
openrl/drivers/offline_driver.py
openrl/drivers/offpolicy_driver.py
openrl/drivers/onpolicy_driver.py
openrl/drivers/rl_driver.py
openrl/envs/__init__.py
openrl/envs/PettingZoo/__init__.py
openrl/envs/PettingZoo/registration.py
openrl/envs/common/__init__.py
openrl/envs/common/build_envs.py
openrl/envs/common/registration.py
openrl/envs/connect_env/__init__.py
openrl/envs/connect_env/base_connect_env.py
openrl/envs/connect_env/connect3_env.py
openrl/envs/connect_env/connect4_env.py
openrl/envs/connect_env/utils.py
openrl/envs/gridworld/__init__.py
openrl/envs/gridworld/gridworld_env.py
openrl/envs/gym_pybullet_drones/__init__.py
openrl/envs/gymnasium/__init__.py
openrl/envs/mpe/__init__.py
openrl/envs/mpe/core.py
openrl/envs/mpe/mpe_env.py
openrl-0.2.0.dist-info/LICENSE
openrl-0.2.0.dist-info/METADATA
openrl-0.2.0.dist-info/WHEEL
openrl-0.2.0.dist-info/entry_points.txt
openrl-0.2.0.dist-info/top_level.txt
openrl-0.2.0.dist-info/RECORD
