Metadata-Version: 2.1
Name: openrl
Version: 0.2.0
Summary: unified reinforcement learning framework
Home-page: https://github.com/OpenRL-Lab/openrl
Author: openrl contributors
Author-email: huangsy1314@163.com
Project-URL: Code, https://github.com/OpenRL-Lab/openrl
Project-URL: Documentation, https://openrl-docs.readthedocs.io/zh/latest/
Keywords: reinforcement-learning multi-agent reinforcement-learning-algorithms pytorch machine-learning baselines toolbox python data-science gym gymnasium
Classifier: Development Status :: 5 - Production/Stable
Classifier: Intended Audience :: Science/Research
Classifier: Topic :: Scientific/Engineering :: Artificial Intelligence
Classifier: Topic :: Software Development :: Libraries :: Python Modules
Classifier: Programming Language :: Python :: 3.8
Classifier: Programming Language :: Python :: 3.9
Classifier: Programming Language :: Python :: 3.10
Classifier: Programming Language :: Python :: 3.11
Classifier: License :: OSI Approved :: Apache Software License
Classifier: Operating System :: OS Independent
Requires-Python: >=3.8
License-File: LICENSE
Requires-Dist: setuptools >=67.0
Requires-Dist: gymnasium >=0.29
Requires-Dist: click
Requires-Dist: termcolor
Requires-Dist: gym
Requires-Dist: torch
Requires-Dist: treevalue
Requires-Dist: rich
Requires-Dist: wandb
Requires-Dist: seaborn
Requires-Dist: jsonargparse
Requires-Dist: imageio
Requires-Dist: opencv-python
Requires-Dist: pygame
Requires-Dist: mujoco
Requires-Dist: tqdm
Requires-Dist: Jinja2
Provides-Extra: atari
Requires-Dist: gymnasium[atari] ; extra == 'atari'
Requires-Dist: gymnasium[accept-rom-license] ; extra == 'atari'
Provides-Extra: dev
Requires-Dist: build ; extra == 'dev'
Requires-Dist: twine ; extra == 'dev'
Provides-Extra: mpe
Requires-Dist: pyglet ==1.5.27 ; extra == 'mpe'
Provides-Extra: nlp
Requires-Dist: transformers ==4.18.0 ; extra == 'nlp'
Requires-Dist: datasets ==2.13 ; extra == 'nlp'
Requires-Dist: nltk ; extra == 'nlp'
Requires-Dist: evaluate ; extra == 'nlp'
Requires-Dist: icetk ; extra == 'nlp'
Provides-Extra: nlp_test
Requires-Dist: transformers ; extra == 'nlp_test'
Requires-Dist: datasets ==2.13 ; extra == 'nlp_test'
Requires-Dist: evaluate ; extra == 'nlp_test'
Provides-Extra: retro
Requires-Dist: gym-retro ; extra == 'retro'
Provides-Extra: selfplay
Requires-Dist: ray[default] >=2.7 ; extra == 'selfplay'
Requires-Dist: ray[serve] ; extra == 'selfplay'
Requires-Dist: async-timeout ; extra == 'selfplay'
Requires-Dist: pettingzoo[classic] ; extra == 'selfplay'
Requires-Dist: trueskill ; extra == 'selfplay'
Provides-Extra: selfplay_test
Requires-Dist: ray[default] >=2.7 ; extra == 'selfplay_test'
Requires-Dist: ray[serve] ; extra == 'selfplay_test'
Requires-Dist: async-timeout ; extra == 'selfplay_test'
Requires-Dist: fastapi ; extra == 'selfplay_test'
Requires-Dist: pettingzoo[mpe] ; extra == 'selfplay_test'
Requires-Dist: pettingzoo[butterfly] ; extra == 'selfplay_test'
Provides-Extra: super_mario
Requires-Dist: gym-super-mario-bros ; extra == 'super_mario'
Provides-Extra: test
Requires-Dist: pytest ; extra == 'test'
Requires-Dist: pytest-cov ; extra == 'test'
Requires-Dist: mypy ; extra == 'test'
Requires-Dist: isort ; extra == 'test'
Requires-Dist: black ; extra == 'test'
Requires-Dist: ruff ; extra == 'test'
Requires-Dist: gpustat ; extra == 'test'
Requires-Dist: gym-super-mario-bros ; extra == 'test'
Requires-Dist: ray[default] >=2.7 ; extra == 'test'
Requires-Dist: ray[serve] ; extra == 'test'
Requires-Dist: async-timeout ; extra == 'test'
Requires-Dist: pettingzoo[classic] ; extra == 'test'
Requires-Dist: trueskill ; extra == 'test'
Requires-Dist: fastapi ; extra == 'test'
Requires-Dist: pettingzoo[mpe] ; extra == 'test'
Requires-Dist: pettingzoo[butterfly] ; extra == 'test'
Requires-Dist: gymnasium[atari] ; extra == 'test'
Requires-Dist: gymnasium[accept-rom-license] ; extra == 'test'
Requires-Dist: transformers ; extra == 'test'
Requires-Dist: datasets ==2.13 ; extra == 'test'
Requires-Dist: evaluate ; extra == 'test'
